gpam_logging/__init__.py
gpam_logging/logger.py
gpam_logging-241497598.dist-info/LICENSE
gpam_logging-241497598.dist-info/METADATA
gpam_logging-241497598.dist-info/WHEEL
gpam_logging-241497598.dist-info/top_level.txt
gpam_logging-241497598.dist-info/RECORD
