Metadata-Version: 2.1
Name: gpam-logging
Version: 241497598
Summary: Logger handler with GPAM integration
Home-page: http://gpam.unb.br
Author: GPAM
Author-email: gpamunb@gmail.com
License: MIT
Platform: UNKNOWN
